__init__.py
MLScienceChallenge_rh/VirtualStainViewer.py
MLScienceChallenge_rh/__init__.py
MLScienceChallenge_rh/demo_virtual_stain_viewer.ipynb
MLScienceChallenge_rh/predict_vs.py
mlsciencechallenge_rh-1.12.dist-info/licenses/LICENSE.txt
mlsciencechallenge_rh-1.12.dist-info/METADATA
mlsciencechallenge_rh-1.12.dist-info/WHEEL
mlsciencechallenge_rh-1.12.dist-info/top_level.txt
mlsciencechallenge_rh-1.12.dist-info/RECORD
