Metadata-Version: 2.4
Name: MLScienceChallenge_rh
Version: 1.12
Summary: ML Science coding challenge for CZI Biohub application.
Author-email: Raymond Hawkins <raymond.hawkins@mail.utoronto.ca>
License-Expression: MIT
Project-URL: Homepage, https://github.com/rayhawkins/MLScienceChallenge
Project-URL: Issues, https://github.com/rayhawkins/MLScienceChallenge/issues
Classifier: Programming Language :: Python :: 3
Classifier: Operating System :: OS Independent
Requires-Python: >=3.10
License-File: LICENSE.txt
Dynamic: license-file
